artefacts_toolkit_chart/__init__.py
artefacts_toolkit_chart/charts.py
artefacts_toolkit_chart/version.py
artefacts_toolkit_chart-1.0.0.dist-info/METADATA
artefacts_toolkit_chart-1.0.0.dist-info/WHEEL
artefacts_toolkit_chart-1.0.0.dist-info/top_level.txt
artefacts_toolkit_chart-1.0.0.dist-info/RECORD
